<?xml version='1.0' encoding='UTF-8'?>
<root>
  <TEXT><![CDATA[


Record date: 2081-12-16

 

 

                           OFFICE NOTE

                      Louisville Care Center

                          43 Riverside Circle

                        Changchun,  LA  14176

 

Xanders, Ruth

MR #564-19-92-7

December 16, 2081

 

Ms. Xanders is a 42-year-old woman with multiple medical problems who

presents for evaluation of chronic hepatitis C.  She reports having

had a blood transfusion in 2059 and has had no history of other

percutaneous exposure including intravenous drug use.  She has had

normal transaminases in the past but a positive hepatitis C

antibody test.  She reports no abdominal pain, nausea or vomiting,

anorexia or weight loss, no diarrhea, constipation, melena or

bright red blood per rectum.  She has had no fevers, chills,

sweats, arthralgias, myalgias or skin rash, epistaxis, easy

bruising or bleeding gums and she has no insomnia or episodes of

confusion.  She reports a generally good energy level with some

mild fatigue.  

 

Past Medical History:

     1.  Hypertension.

     2.  Diabetes.

     3.  Chronic renal insufficiency.

     4.  Hyperlipidemia.

 

Current Medications:  Humulin NPH 20 units qAM, 15 qPM, Humulin

Regular insulin 3 units qAM, 5 qPM, Lipitor 40 mg po q.h.s.,

Procrit 3,000 units sub q. bi week, Lasix 40 mg po q. day, Quinine

260 mg po q.h.s. and Hyzaar 100/25 mg po q. day as well as Naftin

prn.

 

Allergies:  Lisinopril causes cough.

 

Family History:  No history of liver disease or GI malignancies.  

Social History:  She continues to smoke but has cut back recently

and she drinks alcohol approximately once a week to once every two

weeks.  

 

Review of systems otherwise negative for HEENT, cardiovascular,

respiratory, GI, GU, musculoskeletal or neurological systems.

 

On exam, she is a well-appearing woman in no acute distress.  Pulse

80 and regular, blood pressure 152/76, weight 151 pounds.  HEENT

she is anicteric with equal, round, reactive pupils and normal

conjunctivae.  Oropharynx reveals no ulcers or icterus.  Neck

reveals no lymphadenopathy or thyromegaly.  Chest is clear to

auscultation and percussion.  Heart reveals a regular rate and

rhythm, S1 and S2 are present without murmur, rub or gallop.  

Xanders, Ruth

MR #564-19-92-7               -2-            December 16, 2081

 

Abdomen is soft, nontender and non-distended with no

hepatosplenomegaly or masses.  Extremities reveal no clubbing,

cyanosis or edema.  

 

Most recent labs from October 22, 2081 reveal an ALT of 13, AST 19,

alkaline phosphatase 78, bilirubin 0.3, creatinine 3.1, albumin

3.6.  

 

Impression:  Ms. Xanders has a history of a positive hepatitis C

antibody with normal LFT's.  Today, we will check a hepatitis C RNA

level to see if she is in fact viremic or whether she is one of the

lucky 15% of people who clear the virus but remain antibody

positive.  If she does not have hepatitis C RNA in her blood, than

she requires no further workup.  However, if she is RNA positive

than I would suggest a liver biopsy to assess the degree of

inflammation of fibrosis in her liver and make possible plans for

treatment with interferon/ribavirin.  She is amenable to this and

we will follow-up in two weeks by phone to discuss the results of

her RNA test.

 

 

 

Quanterius L. Sorensen, M.D.

 

DD: 12/16/81

DT: 12/19/:1

DV: 12/16/81

 

/renteria

 

cc:

Susan Donaldson, M.D.

Louisville Care Center

38 Shawmut Avenue

Changchun,  LA  14176

 

 ******** Not reviewed by Attending Physician ********





]]></TEXT>
  <TAGS>
    <HYPERLIPIDEMIA id="DOC2" time="before DCT" indicator="mention">
      <HYPERLIPIDEMIA id="HY0" start="1125" end="1139" text="Hyperlipidemia" time="before DCT" indicator="mention" comment=""/>
      <HYPERLIPIDEMIA id="HY1" start="1125" end="1139" text="Hyperlipidemia" time="before DCT" indicator="mention" comment=""/>
      <HYPERLIPIDEMIA id="HY2" start="1125" end="1139" text="Hyperlipidemia" time="before DCT" indicator="mention" comment=""/>
    </HYPERLIPIDEMIA>
    <HYPERLIPIDEMIA id="DOC4" time="during DCT" indicator="mention">
      <HYPERLIPIDEMIA id="HY3" start="1125" end="1139" text="Hyperlipidemia" time="during DCT" indicator="mention" comment=""/>
      <HYPERLIPIDEMIA id="HY4" start="1125" end="1139" text="Hyperlipidemia" time="during DCT" indicator="mention" comment=""/>
      <HYPERLIPIDEMIA id="HY5" start="1125" end="1139" text="Hyperlipidemia" time="during DCT" indicator="mention" comment=""/>
    </HYPERLIPIDEMIA>
    <HYPERLIPIDEMIA id="DOC13" time="after DCT" indicator="mention">
      <HYPERLIPIDEMIA id="HY6" start="1125" end="1139" text="Hyperlipidemia" time="after DCT" indicator="mention" comment=""/>
      <HYPERLIPIDEMIA id="HY7" start="1125" end="1139" text="Hyperlipidemia" time="after DCT" indicator="mention" comment=""/>
      <HYPERLIPIDEMIA id="HY8" start="1125" end="1139" text="Hyperlipidemia" time="after DCT" indicator="mention" comment=""/>
    </HYPERLIPIDEMIA>
    <MEDICATION id="DOC0" time="after DCT" type1="statin" type2="">
      <MEDICATION id="M0" start="1246" end="1253" text="Lipitor" time="after DCT" type1="statin" type2="" comment=""/>
      <MEDICATION id="M1" start="1246" end="1254" text="Lipitor " time="after DCT" type1="statin" type2="" comment=""/>
    </MEDICATION>
    <MEDICATION id="DOC5" time="before DCT" type1="ARB" type2="diuretic">
      <MEDICATION id="M2" start="1361" end="1367" text="Hyzaar" time="before DCT" type1="ARB" type2="diuretic" comment=""/>
      <MEDICATION id="M3" start="1361" end="1367" text="Hyzaar" time="before DCT" type1="ARB" type2="diuretic" comment=""/>
    </MEDICATION>
    <MEDICATION id="DOC6" time="during DCT" type1="ARB" type2="diuretic">
      <MEDICATION id="M4" start="1361" end="1367" text="Hyzaar" time="during DCT" type1="ARB" type2="diuretic" comment=""/>
      <MEDICATION id="M5" start="1361" end="1367" text="Hyzaar" time="during DCT" type1="ARB" type2="diuretic" comment=""/>
    </MEDICATION>
    <MEDICATION id="DOC7" time="after DCT" type1="insulin" type2="">
      <MEDICATION id="M6" start="1167" end="1244" text="Humulin NPH 20 units qAM, 15 qPM, Humulin  Regular insulin 3 units qAM, 5 qPM" time="after DCT" type1="insulin" type2="" comment=""/>
      <MEDICATION id="M7" start="1166" end="1179" text=" Humulin NPH " time="after DCT" type1="insulin" type2="" comment=""/>
      <MEDICATION id="M8" start="1210" end="1225" text="Regular insulin" time="after DCT" type1="insulin" type2="" comment=""/>
      <MEDICATION id="M9" start="1167" end="1174" text="Humulin" time="after DCT" type1="insulin" type2="" comment=""/>
    </MEDICATION>
    <MEDICATION id="DOC11" time="before DCT" type1="statin" type2="">
      <MEDICATION id="M10" start="1246" end="1253" text="Lipitor" time="before DCT" type1="statin" type2="" comment=""/>
      <MEDICATION id="M11" start="1246" end="1254" text="Lipitor " time="before DCT" type1="statin" type2="" comment=""/>
    </MEDICATION>
    <MEDICATION id="DOC12" time="during DCT" type1="statin" type2="">
      <MEDICATION id="M12" start="1246" end="1253" text="Lipitor" time="during DCT" type1="statin" type2="" comment=""/>
      <MEDICATION id="M13" start="1246" end="1254" text="Lipitor " time="during DCT" type1="statin" type2="" comment=""/>
    </MEDICATION>
    <MEDICATION id="DOC14" time="after DCT" type1="ARB" type2="diuretic">
      <MEDICATION id="M14" start="1361" end="1367" text="Hyzaar" time="after DCT" type1="ARB" type2="diuretic" comment=""/>
      <MEDICATION id="M15" start="1361" end="1367" text="Hyzaar" time="after DCT" type1="ARB" type2="diuretic" comment=""/>
    </MEDICATION>
    <MEDICATION id="DOC15" time="before DCT" type1="insulin" type2="">
      <MEDICATION id="M16" start="1167" end="1244" text="Humulin NPH 20 units qAM, 15 qPM, Humulin  Regular insulin 3 units qAM, 5 qPM" time="before DCT" type1="insulin" type2="" comment=""/>
      <MEDICATION id="M17" start="1166" end="1179" text=" Humulin NPH " time="before DCT" type1="insulin" type2="" comment=""/>
      <MEDICATION id="M18" start="1210" end="1225" text="Regular insulin" time="before DCT" type1="insulin" type2="" comment=""/>
      <MEDICATION id="M19" start="1167" end="1174" text="Humulin" time="before DCT" type1="insulin" type2="" comment=""/>
    </MEDICATION>
    <MEDICATION id="DOC18" time="during DCT" type1="insulin" type2="">
      <MEDICATION id="M20" start="1167" end="1244" text="Humulin NPH 20 units qAM, 15 qPM, Humulin  Regular insulin 3 units qAM, 5 qPM" time="during DCT" type1="insulin" type2="" comment=""/>
      <MEDICATION id="M21" start="1166" end="1179" text=" Humulin NPH " time="during DCT" type1="insulin" type2="" comment=""/>
      <MEDICATION id="M22" start="1210" end="1225" text="Regular insulin" time="during DCT" type1="insulin" type2="" comment=""/>
      <MEDICATION id="M23" start="1167" end="1174" text="Humulin" time="during DCT" type1="insulin" type2="" comment=""/>
    </MEDICATION>
    <HYPERTENSION id="DOC1" time="during DCT" indicator="mention">
      <HYPERTENSION id="H0" start="1042" end="1054" text="Hypertension" time="during DCT" indicator="mention" comment=""/>
      <HYPERTENSION id="H1" start="1042" end="1054" text="Hypertension" time="during DCT" indicator="mention" comment=""/>
      <HYPERTENSION id="H2" start="1042" end="1054" text="Hypertension" time="during DCT" indicator="mention" comment=""/>
    </HYPERTENSION>
    <HYPERTENSION id="DOC8" time="during DCT" indicator="high bp">
      <HYPERTENSION id="H3" start="1888" end="1910" text=" blood pressure 152/76" time="during DCT" indicator="high bp" comment=""/>
      <HYPERTENSION id="H4" start="1903" end="1910" text=" 152/76" time="during DCT" indicator="high bp" comment=""/>
      <HYPERTENSION id="H5" start="1904" end="1910" text="152/76" time="during DCT" indicator="high bp" comment=""/>
    </HYPERTENSION>
    <HYPERTENSION id="DOC9" time="after DCT" indicator="mention">
      <HYPERTENSION id="H6" start="1042" end="1054" text="Hypertension" time="after DCT" indicator="mention" comment=""/>
      <HYPERTENSION id="H7" start="1042" end="1054" text="Hypertension" time="after DCT" indicator="mention" comment=""/>
      <HYPERTENSION id="H8" start="1042" end="1054" text="Hypertension" time="after DCT" indicator="mention" comment=""/>
    </HYPERTENSION>
    <HYPERTENSION id="DOC17" time="before DCT" indicator="mention">
      <HYPERTENSION id="H9" start="1042" end="1054" text="Hypertension" time="before DCT" indicator="mention" comment=""/>
      <HYPERTENSION id="H10" start="1042" end="1054" text="Hypertension" time="before DCT" indicator="mention" comment=""/>
      <HYPERTENSION id="H11" start="1042" end="1054" text="Hypertension" time="before DCT" indicator="mention" comment=""/>
    </HYPERTENSION>
    <FAMILY_HIST id="DOC19" indicator="not present">
      <FAMILY_HIST id="F0" indicator="not present"/>
      <FAMILY_HIST id="F1" indicator="not present"/>
      <FAMILY_HIST id="F2" indicator="not present"/>
    </FAMILY_HIST>
    <SMOKER id="DOC16" status="current">
      <SMOKER id="S0" start="1541" end="1564" text=" She continues to smoke" status="current" comment=""/>
      <SMOKER id="S1" start="1542" end="1564" text="She continues to smoke" status="current" comment=""/>
      <SMOKER id="S2" start="1546" end="1564" text="continues to smoke" status="current" comment=""/>
    </SMOKER>
    <DIABETES id="DOC3" time="during DCT" indicator="mention">
      <DIABETES id="D0" start="1066" end="1074" text="Diabetes" time="during DCT" indicator="mention" comment=""/>
      <DIABETES id="D1" start="1066" end="1074" text="Diabetes" time="during DCT" indicator="mention" comment=""/>
      <DIABETES id="D2" start="1066" end="1074" text="Diabetes" time="during DCT" indicator="mention" comment=""/>
    </DIABETES>
    <DIABETES id="DOC10" time="before DCT" indicator="mention">
      <DIABETES id="D3" start="1066" end="1074" text="Diabetes" time="before DCT" indicator="mention" comment=""/>
      <DIABETES id="D4" start="1066" end="1074" text="Diabetes" time="before DCT" indicator="mention" comment=""/>
      <DIABETES id="D5" start="1066" end="1074" text="Diabetes" time="before DCT" indicator="mention" comment=""/>
    </DIABETES>
    <DIABETES id="DOC20" time="after DCT" indicator="mention">
      <DIABETES id="D6" start="1066" end="1074" text="Diabetes" time="after DCT" indicator="mention" comment=""/>
      <DIABETES id="D7" start="1066" end="1074" text="Diabetes" time="after DCT" indicator="mention" comment=""/>
      <DIABETES id="D8" start="1066" end="1074" text="Diabetes" time="after DCT" indicator="mention" comment=""/>
    </DIABETES>
  </TAGS>
</root>
